<?xml version="1.0" encoding="UTF-8"?>
<objects serializationModel="Studio.02.00.00">
	<object class="AudioFile" id="{91c22281-ed43-4620-bffb-9e1954b987a5}">
		<property name="assetPath">
			<value>Success_00.wav</value>
		</property>
		<property name="frequencyInKHz">
			<value>44.0999985</value>
		</property>
		<property name="channelCount">
			<value>2</value>
		</property>
		<property name="length">
			<value>2.7629705215419502</value>
		</property>
		<relationship name="masterAssetFolder">
			<destination>{cea0356b-1c23-4dfb-9afa-76f5e97595eb}</destination>
		</relationship>
	</object>
</objects>
